lightcurvedb/__init__.py
lightcurvedb/config.py
lightcurvedb/managers.py
lightcurvedb/cli/__init__.py
lightcurvedb/cli/ephemeral.py
lightcurvedb/cli/setup.py
lightcurvedb/client/__init__.py
lightcurvedb/client/band.py
lightcurvedb/client/cutouts.py
lightcurvedb/client/lightcurve.py
lightcurvedb/client/measurement.py
lightcurvedb/client/source.py
lightcurvedb/models/__init__.py
lightcurvedb/models/band.py
lightcurvedb/models/cutout.py
lightcurvedb/models/flux.py
lightcurvedb/models/json.py
lightcurvedb/models/source.py
lightcurvedb/simulation/__init__.py
lightcurvedb/simulation/cutouts.py
lightcurvedb/simulation/fluxes.py
lightcurvedb/simulation/sources.py
lightcurvedb-0.0.2.dist-info/METADATA
lightcurvedb-0.0.2.dist-info/WHEEL
lightcurvedb-0.0.2.dist-info/entry_points.txt
lightcurvedb-0.0.2.dist-info/top_level.txt
lightcurvedb-0.0.2.dist-info/RECORD
