Metadata-Version: 2.4
Name: lightcurvedb
Version: 0.0.2
Requires-Python: >=3.11
Requires-Dist: pydantic
Requires-Dist: pydantic-settings
Requires-Dist: sqlmodel
Requires-Dist: numpy
Requires-Dist: pydantic_numpy
Requires-Dist: psycopg_binary
Requires-Dist: asyncpg
Requires-Dist: sqlalchemy[asyncio]
Provides-Extra: dev
Requires-Dist: pytest; extra == "dev"
Requires-Dist: pytest-asyncio; extra == "dev"
Requires-Dist: ruff; extra == "dev"
Requires-Dist: coverage; extra == "dev"
Requires-Dist: pytest-cov; extra == "dev"
Requires-Dist: pre-commit; extra == "dev"
